LICENSE
MANIFEST.in
README.md
requirements.txt
setup.py
onesignal_python.egg-info/PKG-INFO
onesignal_python.egg-info/SOURCES.txt
onesignal_python.egg-info/dependency_links.txt
onesignal_python.egg-info/requires.txt
onesignal_python.egg-info/top_level.txt
onesignalclient/__init__.py
onesignalclient/app_client.py
onesignalclient/base_client.py
onesignalclient/notification.py
onesignalclient/user_client.py
onesignalclient/version.py