Metadata-Version: 1.1
Name: onesignal-python
Version: 0.1.0.dev1
Summary: Python client for OneSignal push notification service
Home-page: https://github.com/joaobarbosa/onesignal-python
Author: João Barbosa
Author-email: joao.ofb@gmail.com
License: MIT
Keywords: onesignal client push notifications api
Platform: UNKNOWN
Classifier: Development Status :: 2 - Pre-Alpha
Classifier: Intended Audience :: Developers
Classifier: Topic :: Software Development :: Libraries :: Python Modules
Classifier: License :: OSI Approved :: MIT License
Classifier: Programming Language :: Python :: 3.3
Classifier: Programming Language :: Python :: 3.4
Classifier: Programming Language :: Python :: 3.5
Classifier: Programming Language :: Python :: 3.6
